coingate/__init__.py
coingate/client.py
coingate/exceptions.py
coingate/http_client.py
coingate/resources/__init__.py
coingate/resources/currency.py
coingate/resources/ledger.py
coingate/resources/order.py
coingate/resources/platform.py
coingate/resources/public.py
coingate/resources/refund.py
coingate/resources/withdrawal.py
coingate/services/__init__.py
coingate/services/ledger.py
coingate/services/order.py
coingate/services/public.py
coingate/services/refund.py
coingate/services/withdrawal.py
coingate/utils.py
coingate_client-1.1.0.dist-info/LICENSE
coingate_client-1.1.0.dist-info/WHEEL
coingate_client-1.1.0.dist-info/METADATA
coingate_client-1.1.0.dist-info/RECORD
