Metadata-Version: 2.1
Name: coingate-client
Version: 1.1.0
Summary: CoinGate Python SDK (API v2)
Home-page: https://github.com/coingate/coingate-python
License: MIT
Keywords: coingate,bitcoin,litecoin,altcoin,merchant,gateway,payment
Author: CoinGate
Author-email: info@coingate.com
Requires-Python: >=3.7,<4.0
Classifier: License :: OSI Approved :: MIT License
Classifier: Programming Language :: Python :: 3
Classifier: Programming Language :: Python :: 3.10
Classifier: Programming Language :: Python :: 3.7
Classifier: Programming Language :: Python :: 3.8
Classifier: Programming Language :: Python :: 3.9
Requires-Dist: pydantic (>=1.9.2,<2.0.0)
Requires-Dist: requests (>=2.28.1,<3.0.0)
Requires-Dist: typing-extensions (>=4.3.0,<5.0.0)
Project-URL: Repository, https://github.com/coingate/coingate-python
